athlon_flex_client/__init__.py
athlon_flex_client/client.py
athlon_flex_client/models/__init__.py
athlon_flex_client/models/profile.py
athlon_flex_client/models/tax_rate.py
athlon_flex_client/models/vehicle.py
athlon_flex_client/models/vehicle_cluster.py
athlon_flex_client/models/filters/__init__.py
athlon_flex_client/models/filters/filter.py
athlon_flex_client/models/filters/vehicle_cluster_filter.py
athlon_flex_client/models/filters/vehicle_filter.py
athlon_flex_client-1.0.3.dist-info/METADATA
athlon_flex_client-1.0.3.dist-info/WHEEL
athlon_flex_client-1.0.3.dist-info/licenses/LICENCE
athlon_flex_client-1.0.3.dist-info/RECORD
