Metadata-Version: 2.4
Name: athlon-flex-client
Version: 1.0.3
Summary: Unofficial Client for the API used by the Athlon Flex Lease showroom
Author-email: Aucke Bos <hedge-cannon-aged@duck.com>
License-File: LICENCE
Requires-Python: >=3.8
Requires-Dist: aiohttp>=3.10.9
Requires-Dist: async-property>=0.2.2
Requires-Dist: nest-asyncio>=1.6.0
Requires-Dist: pkginfo>=1.11
Requires-Dist: pydantic>=2.9.2
Requires-Dist: requests>=2.32.3
